[{"_id":"41bf9a15-9a04-32c5-aad9-f42d03eac490","cvId":"ec5aa0b7-8460-32a2-815f-0902f0da88f2","year":2012,"media":"Automatiseringsgids","title":{"nl_NL":"Agile ontwikkelen vereist andere testaanpak (co-auteur)","uk_UK":"Agile ontwikkelen vereist andere testaanpak (co-auteur)"},"description":{"nl_NL":"Het werken volgens agile-principes verlangt een aanpassing en uitbreiding van de bestaande testactiviteiten. De kwaliteitsaanpak als geheel dient aangepakt te worden. In de context van agile-werkwijzen kunnen we spreken van ‘Agile Quality Assurance’. Testers kunnen zo slagvaardiger optreden.","uk_UK":"Co-author of \"Agile development demands a different test approach\"."},"includeInCv":true},{"_id":"a98b7354-c31f-32cc-bc2c-b22273127fff","cvId":"c8d2bfac-7cb1-3e67-a4c6-c18b32563522","year":2017,"media":"www.valori.nl","title":{"nl_NL":"GDPR-Stubs: het resultaat van een hackathon die dient als katalysator"},"description":{"nl_NL":"Blogartikel over hoe TDM en SV de GDPR wetgeving je een voordeel kunnen geven (in termen van kwaliteit)"},"includeInCv":true},{"_id":"20da67e2-291b-3c59-bba2-9abec9fad0e8","cvId":"c8d2bfac-7cb1-3e67-a4c6-c18b32563522","year":2015,"media":"www.valori.nl","title":{"nl_NL":"Service Virtualisatie: Waardevol voor het Agile team"},"description":{"nl_NL":"Blogartikel over waarom Service Virtualisatie van belang is in Agile teams"},"includeInCv":true},{"_id":"063155e8-c2ed-3e4f-9753-1b7fb9982f17","cvId":"c8d2bfac-7cb1-3e67-a4c6-c18b32563522","year":2014,"media":"Connect-IT 058!","title":{"nl_NL":"Continuous Delivery bij een bank"},"description":{"nl_NL":"Presentatie uit naam van de klant over hoe CD bijdraagt aan het versnellen van het ontwikkelproces"},"includeInCv":true},{"_id":"7e6249b5-c7f6-363c-a858-7c820b16edcb","cvId":"c8d2bfac-7cb1-3e67-a4c6-c18b32563522","year":2019,"media":"Skilled Minds","title":{"nl_NL":"De impact van een DevOps toolchain op beheer"},"description":{"nl_NL":"Presentatie waarom een Toolchain het werk van een beheerder ook positief beïnvloed"},"includeInCv":true},{"_id":"7c95eafb-c9ae-313a-988a-b30bec6648b8","cvId":"c8d2bfac-7cb1-3e67-a4c6-c18b32563522","year":2018,"media":"Webinar","title":{"nl_NL":"Realtime testdata anonymization"},"description":{"nl_NL":"Webinar waarin is getoond hoe je realtime test data kan anonimiseren tijdens de geautomatiseerde testuitvoer"},"includeInCv":true},{"_id":"917b4d9a-8c0c-3333-92e6-1b905f197ccc","cvId":"c8d2bfac-7cb1-3e67-a4c6-c18b32563522","year":2019,"media":"Webinar","title":{"nl_NL":"DATAMasking in Salesforce"},"description":{"nl_NL":"Webinar waarin is verteld aan de wereld hoe de MaskStore functioneel werkt"},"includeInCv":true},{"_id":"12123c69-f3ab-3d83-b453-7c7399927fa5","cvId":"d66f8e9e-d418-3070-9acc-3cbed63fa54e","year":2008,"media":"Diploma","title":{"nl_NL":"tttt"},"description":{"nl_NL":"r34434"},"includeInCv":true},{"_id":"1221edca-1965-3922-8efe-992a2982f391","cvId":"d66f8e9e-d418-3070-9acc-3cbed63fa54e","year":2008,"media":"Diploma","title":{"nl_NL":".NET Masterclass"},"description":{"nl_NL":"BVO Opleidingscentrum"},"includeInCv":true},{"_id":"c8c8a855-3190-335d-884c-12e7af6e3594","cvId":"8701bbd7-e9f0-3f47-bd7c-fa66dc0f211c","year":2014,"media":"CCBS Press","title":{"nl_NL":"World-Wide Workforce, An anatomy of recruiting practices around the globe."},"description":{"nl_NL":"Mede-auteur, onderdeel van minor Cross Cultural Business Skills. ISBN9789079646203"},"includeInCv":true}]